ipfsspec/__init__.py
ipfsspec/async_ipfs.py
ipfsspec/car.py
ipfsspec/tracing.py
ipfsspec/unixfsv1.py
ipfsspec/utils.py
ipfsspec-0.6.0.dist-info/licenses/LICENSE
ipfsspec-0.6.0.dist-info/METADATA
ipfsspec-0.6.0.dist-info/WHEEL
ipfsspec-0.6.0.dist-info/entry_points.txt
ipfsspec-0.6.0.dist-info/top_level.txt
ipfsspec-0.6.0.dist-info/RECORD
