Metadata-Version: 2.4
Name: ipfsspec
Version: 0.6.0
Summary: readonly implementation of fsspec for IPFS
Author-email: Tobias Kölling <tobias.koelling@mpimet.mpg.de>
License: MIT
Keywords: fsspec,IPFS,filesystem
Classifier: Programming Language :: Python :: 3
Classifier: License :: OSI Approved :: MIT License
Classifier: Operating System :: OS Independent
Requires-Python: >=3.9
License-File: LICENSE
Requires-Dist: fsspec>=2024.12.0
Requires-Dist: requests
Requires-Dist: aiohttp
Requires-Dist: aiohttp-retry
Requires-Dist: multiformats
Requires-Dist: dag-cbor>=0.2.2
Requires-Dist: pure-protobuf<3,>=2.1.0
Dynamic: license-file
